modelsafety/__init__.py
modelsafety/client.py
modelsafety/exceptions.py
modelsafety/utils.py
modelsafety-0.1.2.dist-info/LICENSE
modelsafety-0.1.2.dist-info/METADATA
modelsafety-0.1.2.dist-info/WHEEL
modelsafety-0.1.2.dist-info/top_level.txt
modelsafety-0.1.2.dist-info/RECORD
