Metadata-Version: 2.1
Name: modelsafety
Version: 0.1.2
Summary: ModelSafety SDK
Home-page: https://github.com/Curreny/modelsafety-sdk
Author: ModelSafety Team
Author-email: sun_jinzhou@126.com
Keywords: ai,llm,safety,evaluation,audit
Classifier: Development Status :: 4 - Beta
Classifier: Intended Audience :: Developers
Classifier: License :: OSI Approved :: MIT License
Classifier: Programming Language :: Python :: 3
Classifier: Programming Language :: Python :: 3.7
Classifier: Programming Language :: Python :: 3.8
Classifier: Programming Language :: Python :: 3.9
Classifier: Programming Language :: Python :: 3.10
Requires-Python: >=3.7
License-File: LICENSE
Requires-Dist: requests>=2.25.0
